raritygems/__init__.py
raritygems/__main__.py
raritygems/raritygems.py
raritygems/helper/__init__.py
raritygems/helper/config.py
raritygems/helper/helper.py
raritygems/helper/notification.py
raritygems-0.6.0.dist-info/METADATA
raritygems-0.6.0.dist-info/WHEEL
raritygems-0.6.0.dist-info/entry_points.txt
raritygems-0.6.0.dist-info/top_level.txt
raritygems-0.6.0.dist-info/RECORD
