Metadata-Version: 2.1
Name: raritygems
Version: 0.6.0
Summary: Provably Rare Gem: Raritygems
Home-page: https://github.com/jojoee/raritygems
Author: Nathachai Thongniran
Author-email: inid3a@gmail.com
License: UNKNOWN
Platform: UNKNOWN
Classifier: License :: OSI Approved :: MIT License
Classifier: Programming Language :: Python :: 3
Classifier: Programming Language :: Python :: 3.7
